simple_3D_semantic_map/__init__.py
simple_3D_semantic_map/example_0.py
simple_3D_semantic_map/example_1.py
simple_3D_semantic_map/example_2.py
simple_3D_semantic_map/example_3.py
simple_3D_semantic_map/main.py
simple_3D_semantic_map/simple_3D_semantic_map.py
simple_3d_semantic_map-0.1.10.dist-info/LICENSE
simple_3d_semantic_map-0.1.10.dist-info/METADATA
simple_3d_semantic_map-0.1.10.dist-info/WHEEL
simple_3d_semantic_map-0.1.10.dist-info/top_level.txt
simple_3d_semantic_map-0.1.10.dist-info/RECORD
