Metadata-Version: 2.1
Name: simple-3d-semantic-map
Version: 0.1.10
Home-page: https://github.com/Morpheus1024/simple_3D_semantic_map
License: MIT
Classifier: Programming Language :: Python :: 3.9
Classifier: License :: OSI Approved :: MIT License
Classifier: Operating System :: OS Independent
Requires-Python: ==3.9
License-File: LICENSE
Requires-Dist: pyrealsense2 ==2.54.2
Requires-Dist: numpy ==1.26.4
Requires-Dist: matplotlib ==3.8.3
Requires-Dist: torch ==2.3.0
Requires-Dist: open3d ==0.18.0
Requires-Dist: opencv-python ==4.9.0.80
Requires-Dist: transformers ==4.46.1
